samples/__init__.py
samples/account/__init__.py
samples/account/account_client.py
samples/assets/__init__.py
samples/assets/assets_client.py
samples/data/__init__.py
samples/data/data_client.py
samples/data/data_client_event.py
samples/data/data_streaming_client.py
samples/data/data_streaming_client_async.py
samples/data/data_streaming_client_event.py
samples/order/__init__.py
samples/order/order_option_client.py
samples/order/order_stock_client.py
samples/trade/__init__.py
samples/trade/trade_client.py
samples/trade/trade_client_v2.py
samples/trade/trade_client_v3.py
samples/trade/trade_client_v3_event.py
samples/trade/trade_event_client.py
webull/__init__.py
webull/core/__init__.py
webull/core/client.py
webull/core/compat.py
webull/core/headers.py
webull/core/request.py
webull/core/auth/__init__.py
webull/core/auth/credentials.py
webull/core/auth/algorithm/__init__.py
webull/core/auth/algorithm/sha_hmac1.py
webull/core/auth/algorithm/sha_hmac256.py
webull/core/auth/composer/__init__.py
webull/core/auth/composer/default_signature_composer.py
webull/core/auth/signers/__init__.py
webull/core/auth/signers/app_key_signer.py
webull/core/auth/signers/signer.py
webull/core/auth/signers/signer_factory.py
webull/core/cache/__init__.py
webull/core/common/__init__.py
webull/core/common/api_type.py
webull/core/common/easy_enum.py
webull/core/common/region.py
webull/core/context/__init__.py
webull/core/context/request_context_holder.py
webull/core/data/endpoints.json
webull/core/data/retry_config.json
webull/core/endpoint/__init__.py
webull/core/endpoint/chained_endpoint_resolver.py
webull/core/endpoint/default_endpoint_resolver.py
webull/core/endpoint/local_config_regional_endpoint_resolver.py
webull/core/endpoint/resolver_endpoint_request.py
webull/core/endpoint/user_customized_endpoint_resolver.py
webull/core/exception/__init__.py
webull/core/exception/error_code.py
webull/core/exception/error_msg.py
webull/core/exception/exceptions.py
webull/core/http/__init__.py
webull_openapi_python_sdk-1.1.0.dist-info/licenses/LICENSE
webull_openapi_python_sdk-1.1.0.dist-info/licenses/NOTICE
webull_openapi_python_sdk-1.1.0.dist-info/METADATA
webull_openapi_python_sdk-1.1.0.dist-info/WHEEL
webull_openapi_python_sdk-1.1.0.dist-info/top_level.txt
webull_openapi_python_sdk-1.1.0.dist-info/RECORD
