Metadata-Version: 2.4
Name: webull-openapi-python-sdk
Version: 1.1.0
Summary: Webull Python SDK.
Home-page: 
Author: Webull
Author-email: 
License: Apache License 2.0
Platform: any
Requires-Python: >=3.8,<3.12
License-File: LICENSE
License-File: NOTICE
Requires-Dist: jmespath<1.0.0,>=0.9.3
Requires-Dist: cryptography>=2.6.0
Requires-Dist: cachetools==5.2.0
Requires-Dist: paho-mqtt==1.6.1
Requires-Dist: protobuf==4.21.12
Requires-Dist: grpcio==1.51.1
Requires-Dist: grpcio-tools==1.51.1
Dynamic: author
Dynamic: description-content-type
Dynamic: license
Dynamic: license-file
Dynamic: platform
Dynamic: requires-dist
Dynamic: requires-python
Dynamic: summary
